pipeshell/__init__.py
pipeshell/core.py
pipeshell/log.py
pipeshell/pipeline.py
pipeshell-0.9.0.dist-info/METADATA
pipeshell-0.9.0.dist-info/WHEEL
pipeshell-0.9.0.dist-info/RECORD
