Metadata-Version: 2.1
Name: pipeshell
Version: 0.9.0
Summary: A simple pipeline execution library
Home-page: https://github.com/filipecaixeta/pipeshell
License: MIT
Keywords: pipeline,shell,ci
Author: Filipe Caixeta
Author-email: filipecaixeta@gmail.com
Requires-Python: >=3.8,<4.0
Classifier: License :: OSI Approved :: MIT License
Classifier: Programming Language :: Python :: 3
Classifier: Programming Language :: Python :: 3.8
Classifier: Programming Language :: Python :: 3.9
Classifier: Programming Language :: Python :: 3.10
Classifier: Programming Language :: Python :: 3.11
Classifier: Programming Language :: Python :: 3.12
Classifier: Programming Language :: Python :: 3.13
Project-URL: Documentation, https://github.com/filipecaixeta/pipeshell/wiki
Project-URL: Repository, https://github.com/filipecaixeta/pipeshell
